fasttea/__init__.py
fasttea/bootstrap.py
fasttea/html.py
fasttea/picocss.py
fasttea_web-0.3.0.dist-info/LICENSE
fasttea_web-0.3.0.dist-info/METADATA
fasttea_web-0.3.0.dist-info/WHEEL
fasttea_web-0.3.0.dist-info/top_level.txt
fasttea_web-0.3.0.dist-info/RECORD
