Metadata-Version: 2.1
Name: fasttea-web
Version: 0.3.0
Summary: fastTEA - Python-Web-Framework with fastAPI and htmx
Home-page: https://github.com/dein-repo/fasttea
Author: Hebi
Author-email: hebi@python-ninja.com
Classifier: Programming Language :: Python :: 3
Classifier: License :: OSI Approved :: MIT License
Classifier: Operating System :: OS Independent
Requires-Python: >=3.10
License-File: LICENSE
Requires-Dist: pydantic
Requires-Dist: toml
Requires-Dist: fastapi
Requires-Dist: rich
Requires-Dist: uvicorn
